{
    "scopeId": "0000000000000000000186f4",
    "name": "Valle Grande",
    "codigo": "10008",
    "envio": 98.0,
    "census": 2906.0,
    "pollingCensus": 839.0,
    "numStation": 14.0,
    "pollingNumStation": 4.0,
    "pollingPercStation": 28.57,
    "electores": 404.0,
    "sobres": 597.0,
    "nulos": 1.0,
    "percNulos": 0.17,
    "recurridos": 0.0,
    "percRecurridos": 0.0,
    "blancos": 2.0,
    "percBlancos": 0.35,
    "comando": 0.0,
    "percComando": 0.0,
    "impugnados": 3.0,
    "percImpugnados": 0.52,
    "totalVotos": 570.0,
    "afirmativos": 564.0,
    "percAfirmativos": 98.94,
    "abstencion": 269.0,
    "percAbstencion": 32.06,
    "valid": 566.0,
    "percValid": 99.29,
    "recImpCom": 3.0,
    "percRecImpCom": 0.52,
    "participation": 67.93,
    "cargos": 0.0,
    "hayEmpates": false,
    "umbral": 0.0,
    "showCargos": 0.0,
    "isCircus": 1.0,
    "partidos": [
        {
            "code": "134",
            "name": "UNION POR LA PATRIA",
            "codTel": "134",
            "codLogo": "000134",
            "votos": 266.0,
            "perc": 47.16,
            "percCarg": 47.16,
            "cargos": 0.0,
            "candidatos": [
                "SERGIO TOMAS MASSA",
                "AGUSTIN ROSSI"
            ]
        },
        {
            "code": "132",
            "name": "JUNTOS POR EL CAMBIO",
            "codTel": "132",
            "codLogo": "000132",
            "votos": 198.0,
            "perc": 35.1,
            "percCarg": 35.1,
            "cargos": 0.0,
            "candidatos": [
                "PATRICIA BULLRICH",
                "LUIS PETRI"
            ]
        },
        {
            "code": "135",
            "name": "LA LIBERTAD AVANZA",
            "codTel": "135",
            "codLogo": "000135",
            "votos": 83.0,
            "perc": 14.71,
            "percCarg": 14.71,
            "cargos": 0.0,
            "candidatos": [
                "JAVIER GERARDO MILEI",
                "VICTORIA VILLARRUEL"
            ]
        },
        {
            "code": "133",
            "name": "HACEMOS POR NUESTRO PAIS",
            "codTel": "133",
            "codLogo": "000133",
            "votos": 9.0,
            "perc": 1.59,
            "percCarg": 1.59,
            "cargos": 0.0,
            "candidatos": [
                "JUAN SCHIARETTI",
                "FLORENCIO RANDAZZO"
            ]
        },
        {
            "code": "136",
            "name": "FRENTE DE IZQUIERDA Y DE TRABAJADORES - UNIDAD",
            "codTel": "136",
            "codLogo": "000136",
            "votos": 8.0,
            "perc": 1.41,
            "percCarg": 1.41,
            "cargos": 0.0,
            "candidatos": [
                "MYRIAM TERESA BREGMAN",
                "NICOLAS DEL CA\u00d1O"
            ]
        }
    ]
}